pylectormanga/__init__.py
pylectormanga/lectormanga.py
pylectormanga/model.py
pylectormanga/network.py
pylectormanga/page.py
PyLectorManga-0.0.1.dist-info/METADATA
PyLectorManga-0.0.1.dist-info/WHEEL
PyLectorManga-0.0.1.dist-info/top_level.txt
PyLectorManga-0.0.1.dist-info/RECORD
