Metadata-Version: 2.1
Name: PyLectorManga
Version: 0.0.1
Summary: pylectormanga es una biblioteca que te permite buscar manga disponible a través de https://lectormanga.com/. Y podrás acceder a su información.
Home-page: https://github.com/fcoagz/pylectormanga
Author: Francisco Griman
Author-email: Francisco Griman <grihardware@gmail.com>
License: MIT
Project-URL: Homepage, https://github.com/fcoagz/pylectormanga
Project-URL: Bug Tracker, https://github.com/fcoagz/pylectormanga/issues
Keywords: Manga,Lector Manga,PyLectorManga
Classifier: Programming Language :: Python :: 3
Classifier: License :: OSI Approved :: MIT License
Classifier: Operating System :: OS Independent
Requires-Python: >=3.9
Requires-Dist: bs4
Requires-Dist: cfscrape
Requires-Dist: requests
Requires-Dist: urllib3 <2
